[
  { "state": "Alabama", "cities": ["Birmingham", "Montgomery", "Mobile"] },
  { "state": "Alaska", "cities": ["Anchorage", "Fairbanks", "Juneau"] },
  { "state": "Arizona", "cities": ["Phoenix", "Tucson", "Mesa"] },
  { "state": "Arkansas", "cities": ["Little Rock", "Fayetteville", "Fort Smith"] },
  { "state": "California", "cities": ["Los Angeles", "San Francisco", "San Diego"] },
  { "state": "Colorado", "cities": ["Denver", "Colorado Springs", "Aurora"] },
  { "state": "Connecticut", "cities": ["Bridgeport", "New Haven", "Hartford"] },
  { "state": "Delaware", "cities": ["Wilmington", "Dover", "Newark"] },
  { "state": "Florida", "cities": ["Miami", "Orlando", "Tampa"] },
  { "state": "Georgia", "cities": ["Atlanta", "Savannah", "Augusta"] },
  { "state": "Hawaii", "cities": ["Honolulu", "Hilo", "Kailua"] },
  { "state": "Idaho", "cities": ["Boise", "Meridian", "Nampa"] },
  { "state": "Illinois", "cities": ["Chicago", "Springfield", "Naperville"] },
  { "state": "Indiana", "cities": ["Indianapolis", "Fort Wayne", "Evansville"] },
  { "state": "Iowa", "cities": ["Des Moines", "Cedar Rapids", "Davenport"] },
  { "state": "Kansas", "cities": ["Wichita", "Overland Park", "Kansas City"] },
  { "state": "Kentucky", "cities": ["Louisville", "Lexington", "Bowling Green"] },
  { "state": "Louisiana", "cities": ["New Orleans", "Baton Rouge", "Shreveport"] },
  { "state": "Maine", "cities": ["Portland", "Lewiston", "Bangor"] },
  { "state": "Maryland", "cities": ["Baltimore", "Annapolis", "Frederick"] },
  { "state": "Massachusetts", "cities": ["Boston", "Worcester", "Springfield"] },
  { "state": "Michigan", "cities": ["Detroit", "Grand Rapids", "Ann Arbor"] },
  { "state": "Minnesota", "cities": ["Minneapolis", "Saint Paul", "Rochester"] },
  { "state": "Mississippi", "cities": ["Jackson", "Gulfport", "Hattiesburg"] },
  { "state": "Missouri", "cities": ["Kansas City", "Saint Louis", "Springfield"] },
  { "state": "Montana", "cities": ["Billings", "Missoula", "Great Falls"] },
  { "state": "Nebraska", "cities": ["Omaha", "Lincoln", "Bellevue"] },
  { "state": "Nevada", "cities": ["Las Vegas", "Reno", "Henderson"] },
  { "state": "New Hampshire", "cities": ["Manchester", "Nashua", "Concord"] },
  { "state": "New Jersey", "cities": ["Newark", "Jersey City", "Paterson"] },
  { "state": "New Mexico", "cities": ["Albuquerque", "Santa Fe", "Las Cruces"] },
  { "state": "New York", "cities": ["New York City", "Buffalo", "Rochester"] },
  { "state": "North Carolina", "cities": ["Charlotte", "Raleigh", "Greensboro"] },
  { "state": "North Dakota", "cities": ["Fargo", "Bismarck", "Grand Forks"] },
  { "state": "Ohio", "cities": ["Columbus", "Cleveland", "Cincinnati"] },
  { "state": "Oklahoma", "cities": ["Oklahoma City", "Tulsa", "Norman"] },
  { "state": "Oregon", "cities": ["Portland", "Salem", "Eugene"] },
  { "state": "Pennsylvania", "cities": ["Philadelphia", "Pittsburgh", "Harrisburg"] },
  { "state": "Rhode Island", "cities": ["Providence", "Warwick", "Cranston"] },
  { "state": "South Carolina", "cities": ["Charleston", "Columbia", "North Charleston"] },
  { "state": "South Dakota", "cities": ["Sioux Falls", "Rapid City", "Aberdeen"] },
  { "state": "Tennessee", "cities": ["Nashville", "Memphis", "Knoxville"] },
  { "state": "Texas", "cities": ["Houston", "Dallas", "Austin"] },
  { "state": "Utah", "cities": ["Salt Lake City", "West Valley City", "Provo"] },
  { "state": "Vermont", "cities": ["Burlington", "South Burlington", "Rutland"] },
  { "state": "Virginia", "cities": ["Virginia Beach", "Richmond", "Norfolk"] },
  { "state": "Washington", "cities": ["Seattle", "Spokane", "Tacoma"] },
  { "state": "West Virginia", "cities": ["Charleston", "Huntington", "Morgantown"] },
  { "state": "Wisconsin", "cities": ["Milwaukee", "Madison", "Green Bay"] },
  { "state": "Wyoming", "cities": ["Cheyenne", "Casper", "Laramie"] }
]